alipay_faas_server_sdk/__init__.py
alipay_faas_server_sdk/cloud.py
alipay_faas_server_sdk/config/__init__.py
alipay_faas_server_sdk/config/cloud_config.py
alipay_faas_server_sdk/context/__init__.py
alipay_faas_server_sdk/context/alipay_context.py
alipay_faas_server_sdk/context/fn_context.py
alipay_faas_server_sdk/function/__init__.py
alipay_faas_server_sdk/function/fn_client.py
alipay_faas_server_sdk/function/fn_request.py
alipay_faas_server_sdk/function/fn_response.py
alipay_faas_server_sdk/http/__init__.py
alipay_faas_server_sdk/http/http_client.py
alipay_faas_server_sdk/http/http_constants.py
alipay_faas_server_sdk/http/http_request.py
alipay_faas_server_sdk/http/http_response.py
alipay_faas_server_sdk/utils/__init__.py
alipay_faas_server_sdk/utils/env_util.py
alipay_faas_server_sdk/utils/hash_util.py
alipay_faas_server_sdk-0.0.3.dist-info/LICENSE
alipay_faas_server_sdk-0.0.3.dist-info/METADATA
alipay_faas_server_sdk-0.0.3.dist-info/WHEEL
alipay_faas_server_sdk-0.0.3.dist-info/top_level.txt
alipay_faas_server_sdk-0.0.3.dist-info/RECORD
